livisi/__init__.py
livisi/livisi_connector.py
livisi/livisi_const.py
livisi/livisi_controller.py
livisi/livisi_device.py
livisi/livisi_errors.py
livisi/livisi_event.py
livisi/livisi_json_util.py
livisi/livisi_websocket.py
livisi/livisi_websocket_event.py
livisi-1.0.1.dist-info/licenses/LICENSE
livisi-1.0.1.dist-info/METADATA
livisi-1.0.1.dist-info/WHEEL
livisi-1.0.1.dist-info/top_level.txt
livisi-1.0.1.dist-info/RECORD
